jaraco/video/__init__.py
jaraco/video/capture.py
jaraco/video/util.py
jaraco/video/api/__init__.py
jaraco/video/api/objects.py
jaraco/video/api/DirectShow/DexterLib.idl
jaraco/video/api/DirectShow/DexterLib.tlb
jaraco/video/api/DirectShow/DirectShow.tlb
jaraco.video-4.0.2.dist-info/LICENSE
jaraco.video-4.0.2.dist-info/METADATA
jaraco.video-4.0.2.dist-info/WHEEL
jaraco.video-4.0.2.dist-info/entry_points.txt
jaraco.video-4.0.2.dist-info/top_level.txt
jaraco.video-4.0.2.dist-info/RECORD
