Metadata-Version: 2.1
Name: jaraco.video
Version: 4.0.2
Summary: A pure-python framegrabber for Windows
Home-page: https://github.com/jaraco/jaraco.video
Author: Jason R. Coombs
Author-email: jaraco@jaraco.com
License: UNKNOWN
Platform: UNKNOWN
Classifier: Development Status :: 5 - Production/Stable
Classifier: Intended Audience :: Developers
Classifier: License :: OSI Approved :: MIT License
Classifier: Programming Language :: Python :: 3
Classifier: Programming Language :: Python :: 3 :: Only
Classifier: Operating System :: Microsoft :: Windows
Classifier: Topic :: Multimedia :: Video :: Capture
Requires-Python: >=3.6
Requires-Dist: comtypes
Requires-Dist: Pillow
Requires-Dist: jaraco.structures
Provides-Extra: docs
Requires-Dist: sphinx ; extra == 'docs'
Requires-Dist: jaraco.packaging (>=8.2) ; extra == 'docs'
Requires-Dist: rst.linker (>=1.9) ; extra == 'docs'
Provides-Extra: testing
Requires-Dist: pytest (>=4.6) ; extra == 'testing'
Requires-Dist: pytest-checkdocs (>=2.4) ; extra == 'testing'
Requires-Dist: pytest-flake8 ; extra == 'testing'
Requires-Dist: pytest-cov ; extra == 'testing'
Requires-Dist: pytest-enabler (>=1.0.1) ; extra == 'testing'
Requires-Dist: pytest-black (>=0.3.7) ; (platform_python_implementation != "PyPy" and python_version < "3.10") and extra == 'testing'
Requires-Dist: pytest-mypy ; (platform_python_implementation != "PyPy" and python_version < "3.10") and extra == 'testing'
